MANIFEST.in
README.md
requirements.txt
setup.py
tests/__init__.py
tests/test_settings.py
tests/urls.py
threebot/__init__.py
threebot/admin.py
threebot/botconnection.py
threebot/forms.py
threebot/models.py
threebot/tasks.py
threebot/tests.py
threebot/urls.py
threebot/utils.py
threebot.egg-info/PKG-INFO
threebot.egg-info/SOURCES.txt
threebot.egg-info/dependency_links.txt
threebot.egg-info/requires.txt
threebot.egg-info/top_level.txt
threebot/migrations/0001_initial.py
threebot/migrations/0002_auto_20150703_1354.py
threebot/migrations/0003_auto_20170505_1012.py
threebot/migrations/__init__.py
threebot/static/threebot/.do-not-remove
threebot/static/threebot/css/3bot.css
threebot/static/threebot/css/bootstrap-theme.css
threebot/static/threebot/css/bootstrap-theme.css.map
threebot/static/threebot/css/bootstrap-theme.min.css
threebot/static/threebot/css/bootstrap.css
threebot/static/threebot/css/bootstrap.css.map
threebot/static/threebot/css/bootstrap.min.css
threebot/static/threebot/css/sortable.css
threebot/static/threebot/fonts/glyphicons-halflings-regular.eot
threebot/static/threebot/fonts/glyphicons-halflings-regular.svg
threebot/static/threebot/fonts/glyphicons-halflings-regular.ttf
threebot/static/threebot/fonts/glyphicons-halflings-regular.woff
threebot/static/threebot/img/logo_1000k.png
threebot/static/threebot/img/logo_128.png
threebot/static/threebot/img/logo_152.png
threebot/static/threebot/img/silberpfeil.jpg
threebot/static/threebot/js/bootstrap.js
threebot/static/threebot/js/bootstrap.min.js
threebot/static/threebot/js/jquery-autosize.js
threebot/static/threebot/js/jquery-sortable.js
threebot/static/threebot/js/jquery.js
threebot/templates/404.html
threebot/templates/500.html
threebot/templates/base.html
threebot/templates/bootstrap_base.html
threebot/templates/organizations_base.html
threebot/templates/organizations/login.html
threebot/templates/organizations/myorgs.html
threebot/templates/organizations/organization_confirm_delete.html
threebot/templates/organizations/organization_detail.html
threebot/templates/organizations/organization_form.html
threebot/templates/organizations/organization_list.html
