Metadata-Version: 1.0
Name: threebot
Version: 0.1.1
Summary: 3bot is an open-source software platform to build, configure and perform your repetitive tasks.
Home-page: UNKNOWN
Author: arteria GmbH
Author-email: renner@arteria.ch
License: UNKNOWN
Platform: UNKNOWN
